pysoundanalyser/__init__.py
pysoundanalyser/__main__.py
pysoundanalyser/_version_info.py
pysoundanalyser/audio_manager.py
pysoundanalyser/dialog_apply_filter.py
pysoundanalyser/dialog_change_channel.py
pysoundanalyser/dialog_concatenate.py
pysoundanalyser/dialog_cut.py
pysoundanalyser/dialog_edit_preferences.py
pysoundanalyser/dialog_generate_noise.py
pysoundanalyser/dialog_generate_sinusoid.py
pysoundanalyser/dialog_generate_sound.py
pysoundanalyser/dialog_get_font.py
pysoundanalyser/dialog_resample.py
pysoundanalyser/dialog_save_sound.py
pysoundanalyser/global_parameters.py
pysoundanalyser/pyqtver.py
pysoundanalyser/qrc_resources.py
pysoundanalyser/random_id.py
pysoundanalyser/sndlib.py
pysoundanalyser/threaded_plotters.py
pysoundanalyser/utilities_open_manual.py
pysoundanalyser/utility_functions.py
pysoundanalyser/wavpy.py
pysoundanalyser/wavpy_sndf.py
pysoundanalyser/win_acf_plot.py
pysoundanalyser/win_autocorrelogram_plot.py
pysoundanalyser/win_generic_plot.py
pysoundanalyser/win_spectrogram_plot.py
pysoundanalyser/win_spectrum_plot.py
pysoundanalyser/win_waveform_plot.py
pysoundanalyser/doc/Makefile
pysoundanalyser/doc/conf.py
pysoundanalyser/doc/index.rst
pysoundanalyser/doc/installation.rst
pysoundanalyser/doc/intro.rst
pysoundanalyser/doc/make.bat
pysoundanalyser/doc/mkdoc.sh
pysoundanalyser/doc/requirements.txt
pysoundanalyser/doc/user_interface.rst
pysoundanalyser/doc/_build/html/.buildinfo
pysoundanalyser/doc/_build/html/genindex.html
pysoundanalyser/doc/_build/html/index.html
pysoundanalyser/doc/_build/html/installation.html
pysoundanalyser/doc/_build/html/intro.html
pysoundanalyser/doc/_build/html/objects.inv
pysoundanalyser/doc/_build/html/search.html
pysoundanalyser/doc/_build/html/searchindex.js
pysoundanalyser/doc/_build/html/user_interface.html
pysoundanalyser/doc/_build/html/_sources/index.rst.txt
pysoundanalyser/doc/_build/html/_sources/installation.rst.txt
pysoundanalyser/doc/_build/html/_sources/intro.rst.txt
pysoundanalyser-0.3.7.dist-info/COPYING.txt
pysoundanalyser-0.3.7.dist-info/METADATA
pysoundanalyser-0.3.7.dist-info/WHEEL
pysoundanalyser-0.3.7.dist-info/entry_points.txt
pysoundanalyser-0.3.7.dist-info/top_level.txt
pysoundanalyser-0.3.7.dist-info/RECORD
